agentmesh/__init__.py
agentmesh/common/__init__.py
agentmesh/common/config/config_manager.py
agentmesh/common/enums/__init__.py
agentmesh/common/enums/model_enums.py
agentmesh/common/utils/__init__.py
agentmesh/common/utils/config_util.py
agentmesh/common/utils/loading_indicator.py
agentmesh/common/utils/log.py
agentmesh/common/utils/string_util.py
agentmesh/common/utils/xml_util.py
agentmesh/models/__init__.py
agentmesh/models/model_factory.py
agentmesh/models/llm/__init__.py
agentmesh/models/llm/base_model.py
agentmesh/models/llm/claude_model.py
agentmesh/models/llm/deepseek_model.py
agentmesh/models/llm/openai_model.py
agentmesh/protocal/__init__.py
agentmesh/protocal/agent.py
agentmesh/protocal/context.py
agentmesh/protocal/message.py
agentmesh/protocal/result.py
agentmesh/protocal/task.py
agentmesh/protocal/team.py
agentmesh/tools/__init__.py
agentmesh/tools/base_tool.py
agentmesh/tools/browser_tool.py
agentmesh/tools/tool_manager.py
agentmesh/tools/browser/browser_action.py
agentmesh/tools/browser/browser_tool.py
agentmesh/tools/calculator/calculator.py
agentmesh/tools/current_time/current_time.py
agentmesh/tools/file_save/__init__.py
agentmesh/tools/file_save/file_save.py
agentmesh/tools/google_search/google_search.py
agentmesh/tools/terminal/__init__.py
agentmesh/tools/terminal/terminal.py
agentmesh_sdk-0.1.4.dist-info/LICENSE
agentmesh_sdk-0.1.4.dist-info/METADATA
agentmesh_sdk-0.1.4.dist-info/WHEEL
agentmesh_sdk-0.1.4.dist-info/top_level.txt
agentmesh_sdk-0.1.4.dist-info/RECORD
